MANIFEST.in
README
setup.cfg
setup.py
extract/__init__.py
extract/build_manpage.py
extract/data.py
extract/version.py
geonode_extract.egg-info/PKG-INFO
geonode_extract.egg-info/SOURCES.txt
geonode_extract.egg-info/dependency_links.txt
geonode_extract.egg-info/requires.txt
geonode_extract.egg-info/top_level.txt
scripts/geonode-extract