Metadata-Version: 1.0
Name: geonode-extract
Version: 0.4.2
Summary: Extract data from a geonode and put it in a folder
Home-page: http://github.com/GFDRR/geonode-extract
Author: Ariel Núñez
Author-email: ingenieroariel@gmail.com
License: BSD
Keywords: gis vector feature raster data
Platform: UNKNOWN
Classifier: Development Status :: 4 - Beta
Classifier: Intended Audience :: Developers
Classifier: Intended Audience :: Science/Research
Classifier: License :: OSI Approved :: BSD License
Classifier: Operating System :: OS Independent
Classifier: Programming Language :: Python
Classifier: Topic :: Scientific/Engineering :: GIS
